{
    "0": "Kiss the persone sitting left to you !",
    "1": "Remove any piece of the dress and wear it after 5 rounds of game !",
    "2": "Let the other players go through your phone for two minutes !",
    "3": "Get an item from the bathroom and sell it to the group for 3 minutes !",
    "4": "Let another person draw a tattoo on your back with a marker !",
    "5": "Drink a mystery drink created by the rest of the group !",
    "6": "Show your search history on your phone !",
    "7": "Pretend to be the person on your left for 10 minutes !",
    "8": "Whisper a secret to the person on your left !",
    "9": "Eat something of the groups choice without using your hands !",
    "10": "Let another person in the group touch up your makeup !",
    "11": "Choose a consenting partner and try to get into one of these wild sex positions (clothes on) !",
    "12": "Make eye contact with the person to your right and moan for 5 seconds !",
    "13": "Make your orgasm face at the person opposite to you for 5 seconds !",
    "14": "Seductively eat a something, by locking eyes with the person to your left !",
    "15": "Perform a seductive dance in front of the group for 15 seconds !",
    "16": "Pick up the nearest object to you and demonstrate how to put on protection !",
    "17": "Google the dirtiest thing you can think of and show it to the group !",
    "18": "Give a personalised insult to everyone in the room !",
    "19": "Close your eyes, sit on someone’s lap and guess who it is !",
    "20": "Argue with a wall and pretend like it talks back for one minute !",
    "21": "Exchange an item of clothing with the player on your right !",
    "22": "Put on a blindfold and eat whatever the group gives you !",
    "23": "Say something dirty to the person on your left !",
    "24": "Give a foot massage to the person on your right !",
    "25": "Give a lap dance to someone of your choice, in this group !",
    "26": "Repeat everything the person on your right is saying until it's your turn again !",
    "27": "Remove 2 items of clothing !",
    "28": "Keep your eyes closed until it's your turn again !",
    "29": "Do your best sexy crawl !",
    "30": "Whisper a secret to the person on your left !",
    "31": "Try and make the group laugh as quickly as possible !",
    "32": "Bark like a Dog for 1 minute !",
    "33": "Let someone else tickle you and try not to laugh !",
    "34": "Tell the group two truths and a lie, and they have to guess which one the lie is !",
    "35": "For the next 10 minutes, every time someone asks you something, respond with a bark !",
    "36": "Put your mouth near to the mouth of any person in the group, but don't kiss !",
    "37": "Show your panty which you wore to group !",
    "38": "Close your eyes and guess which body part !",
    "39": "Let someone in the group spank you !",
    "40": "Close your eyes and open your mouth for 1 min !",
    "41": "Wear your clothes backwards for the rest of the game !",
    "42": "Wear your clothes inside out for the rest of the game !",
    "43": "Get slapped on the face by the person of your choosing !",
    "44": "Switch clothes with someone of the opposite sex in the group !",
    "45": "Show off the color of your boxers !",
    "46": "Demonstrate your oral sex technique on the nearest appropriate object !",
    "47": "Demonstrate your hand job technique on the nearest appropriate object !",
    "48": "Spin an empty bottle and kiss whoever it lands on !",
    "49": "Do a striptease for the group 1",
    "50": "Swap shirts with someone in the room !"
}